Metadata-Version: 2.1
Name: slc.zopescript
Version: 1.1.1
Summary: Base classes for running code as Zope console scripts
Home-page: http://pypi.python.org/pypi/slc.zopescript
Author: Syslab.com GmbH
Author-email: info@syslab.com
License: BSD
Keywords: Zope console script
Platform: UNKNOWN
Classifier: Framework :: Zope2
Classifier: Programming Language :: Python
Classifier: Programming Language :: Python :: 2.7
Provides-Extra: test
Provides-Extra: develop
